{
    "data":[
        {
            "channel": "retail",
            "country": "CA",
            "directory_image_url": "",
            "display_city": "Calgary",
            "display_location": "Calgary",
            "display_name": "Chinook Centre",
            "display_postal_code": "T2H 0K8",
            "display_state": "Alberta",
            "display_street_address_1": "6455 Macleod Trail SW CRU# 150G ",
            "display_street_address_2": "",
            "email": "calgary@onepeloton.ca",
            "google_maps_url": "https://www.google.com/maps/place/CF+Chinook+Centre/@50.9984995,-114.0755336,17z/data=!3m2!4b1!5s0x53717055f3038373:0x962a51b6d76ffe30!4m5!3m4!1s0x537170558c817a7b:0xa80ab79074859579!8m2!3d50.9984961!4d-114.0733449",
            "hero_image_url": "",
            "hours": {
                "mon": "10:00 AM - 9:00 PM",
                "tue": "10:00 AM - 9:00 PM",
                "wed": "10:00 AM - 9:00 PM",
                "thu": "10:00 AM - 9:00 PM",
                "fri": "10:00 AM - 9:00 PM",
                "sat": "10:00 AM - 9:00 PM",
                "sun": "10:00 AM - 6:00 PM"
            },
            "hours_of_operation": [
                "Mon - Sat: 11:00 a.m. - 7:00 p.m.",
                " Sun: 11:00 a.m. - 6:00 p.m."
            ],
            "id": "ea9ef0af0d604b5197b4ccbf984a1cc8",
            "is_coming_soon": false,
            "is_microstore": false,
            "is_visible": true,
            "is_third_party": false,
            "is_booking_available": true,
            "image_urls": [],
            "latitude": 50.9985,
            "longitude": -114.073345,
            "meta_description": "",
            "meta_title": "",
            "name": "CA Calgary",
            "phone_ext": "",
            "region": "Alberta",
            "slug": "can_ab_calgary_2",
            "shipping_phone_number": "(587) 317-7146",
            "stripe_location": "tml_EZJGCAjervp8Tf"
        },
        {
            "channel": "retail",
            "country": "US",
            "directory_image_url": "",
            "display_city": "Bellevue",
            "display_location": "Bellevue",
            "display_name": "Bellevue Square",
            "display_postal_code": "98004",
            "display_state": "WA",
            "display_street_address_1": "233 Bellevue Square",
            "display_street_address_2": "",
            "email": "bellevue@onepeloton.com",
            "google_maps_url": "https://www.google.com/maps/place/Peloton/@47.6117405,-122.2034958,17z/data=!3m2!4b1!5s0x54906c85ec8e2ad9:0x663c92cce9c8b5bb!4m5!3m4!1s0x54906c85e5cb1b63:0x10b14fde2e2ce222!8m2!3d47.6117405!4d-122.2013071",
            "hero_image_url": "",
            "hours": {
                "mon": "10:00 AM \u2013 9:00 PM",
                "tue": "10:00 AM \u2013 9:00 PM",
                "wed": "10:00 AM \u2013 9:00 PM",
                "thu": "10:00 AM \u2013 9:00 PM",
                "fri": "10:00 AM \u2013 9:00 PM",
                "sat": "10:00 AM \u2013 9:00 PM",
                "sun": "11:00 AM \u2013 7:00 PM"
            },
            "hours_of_operation": [
                "Mon - Sat: 10:00 a.m. - 9:00 p.m.",
                "Sun: 11:00 a.m. - 7:00 p.m."
            ],
            "id": "ec8253cca7784d5daf423fbbfee0d66f",
            "is_coming_soon": false,
            "is_microstore": false,
            "is_visible": true,
            "is_third_party": false,
            "is_booking_available": true,
            "image_urls": [],
            "latitude": 47.615852,
            "longitude": -122.206275,
            "meta_description": "",
            "meta_title": "",
            "name": "Peloton Bellevue",
            "phone_ext": "",
            "region": "Washington",
            "slug": "seattle",
            "shipping_phone_number": "(425) 414-7190",
            "stripe_location": "tml_EZJGCQwdnz2TmJ"
        },{
            "channel": "retail",
            "country": "US",
            "directory_image_url": "",
            "display_city": "Portland",
            "display_location": "Portland",
            "display_name": "Washington Square",
            "display_postal_code": "97223",
            "display_state": "OR",
            "display_street_address_1": "9374 SW Washington Square Road",
            "display_street_address_2": "Space R-05",
            "email": "portland@onepeloton.com",
            "google_maps_url": "https://www.google.com/maps/place/9374+SW+Washington+Square+Rd+Space+R-05,+Tigard,+OR+97223/data=!4m2!3m1!1s0x54950cf8e9624505:0x496bda291bc7091?sa=X&ved=2ahUKEwix186xypD0AhUNm-AKHauuBAkQ8gF6BAgGEAE",
            "hero_image_url": "",
            "hours": {
                "mon": "10:00 AM - 9:00 PM",
                "tue": "10:00 AM - 9:00 PM",
                "wed": "10:00 AM - 9:00 PM",
                "thu": "10:00 AM - 9:00 PM",
                "fri": "10:00 AM - 9:00 PM",
                "sat": "10:00 AM - 9:00 PM",
                "sun": "11:00 AM - 7:00 PM"
            },
            "hours_of_operation": [
                "Mon - Sat: 10:00 a.m. - 9:00 p.m.",
                " Sun: 11:00 a.m. - 7:00 p.m."
            ],
            "id": "dfd3e2d22aa34e9caa9d7d7ee76781e0",
            "is_coming_soon": false,
            "is_microstore": false,
            "is_visible": true,
            "is_third_party": false,
            "is_booking_available": true,
            "image_urls": [],
            "latitude": 45.450258,
            "longitude": -122.781309,
            "meta_description": "",
            "meta_title": "",
            "name": "Peloton Portland",
            "phone_ext": "",
            "region": "Oregon",
            "slug": "us_or_portland_2",
            "shipping_phone_number": "(503) 549-1069 ",
            "stripe_location": "tml_EZCjDAefa6WO7f"
        },
        {
            "channel": "retail",
            "country": "US",
            "directory_image_url": "",
            "display_city": "Roseville",
            "display_location": "Roseville",
            "display_name": "Westfield Galleria at Roseville",
            "display_postal_code": "95678",
            "display_state": "CA",
            "display_street_address_1": "1151 Galleria Blvd",
            "display_street_address_2": "Suite 157",
            "email": "roseville@onepeloton.com",
            "google_maps_url": "https://www.google.com/maps/place/1173+Galleria+Blvd+Space+157,+Roseville,+CA+95678/@38.7730243,-121.2733643,17z/data=!3m2!4b1!5s0x809b21d130508db7:0x663c92ccfc552bcb!4m13!1m7!3m6!1s0x809b21d0f58ed4ff:0x27ef4155bc882432!2s1173+Galleria+Blvd+Space+157,+Roseville,+CA+95678!3b1!8m2!3d38.7730243!4d-121.2711756!3m4!1s0x809b21d0f58ed4ff:0x27ef4155bc882432!8m2!3d38.7730243!4d-121.2711756",
            "hero_image_url": "",
            "hours": {
                "mon": "10:00 AM - 9:00 PM",
                "tue": "10:00 AM - 9:00 PM",
                "wed": "10:00 AM - 9:00 PM",
                "thu": "10:00 AM - 9:00 PM",
                "fri": "10:00 AM - 9:00 PM",
                "sat": "10:00 AM - 9:00 PM",
                "sun": "11:00 AM - 7:00 PM"
            },
            "hours_of_operation": [
                "Mon - Sat: 10:00 a.m. - 9:00 p.m.",
                "Sun: 11:00 a.m. - 7:00 p.m."
            ],
            "id": "ba6a9c7e21d149e2b7677001e853e37f",
            "is_coming_soon": false,
            "is_microstore": false,
            "is_visible": true,
            "is_third_party": false,
            "is_booking_available": true,
            "image_urls": [],
            "latitude": 38.773024,
            "longitude": -121.273364,
            "meta_description": "",
            "meta_title": "",
            "name": "Peloton Roseville",
            "phone_ext": "",
            "region": "California",
            "slug": "us_ca_roseville_2",
            "shipping_phone_number": "(916) 249-7833",
            "stripe_location": "tml_EZJGAwKiF94feb"
        },{
            "channel": "retail",
            "country": "US",
            "directory_image_url": "",
            "display_city": "Murray",
            "display_location": "Murray",
            "display_name": "Fashion Place",
            "display_postal_code": "84017",
            "display_state": "UT",
            "display_street_address_1": "6191 State Street",
            "display_street_address_2": "",
            "email": "murray@onepeloton.com",
            "google_maps_url": "https://www.google.com/maps/place/Peloton/@40.6359267,-111.8861761,15z/data=!4m5!3m4!1s0x0:0xff84b9f58a530296!8m2!3d40.6359267!4d-111.8861761",
            "hero_image_url": "",
            "hours": {
                "mon": "11:00 AM \u2013 8:00 PM",
                "tue": "11:00 AM \u2013 8:00 PM",
                "wed": "11:00 AM \u2013 8:00 PM",
                "thu": "11:00 AM \u2013 8:00 PM",
                "fri": "10:00 AM \u2013 9:00 PM",
                "sat": "10:00 AM \u2013 9:00 PM",
                "sun": "12:00 PM \u2013 6:00 PM"
            },
            "hours_of_operation": [
                "Mon - Thurs: 11:00 a.m. - 8:00 p.m.",
                " Fri - Sat: 10:00 a.m. - 9:00 p.m.",
                " Sun: 12:00 p.m. - 6:00 p.m."
            ],
            "id": "77f2ca40d18f47349621366bd2c9fa3d",
            "is_coming_soon": false,
            "is_microstore": false,
            "is_visible": true,
            "is_third_party": false,
            "is_booking_available": true,
            "image_urls": [],
            "latitude": 40.636181,
            "longitude": -111.888273,
            "meta_description": "",
            "meta_title": "",
            "name": "Peloton Murray",
            "phone_ext": "",
            "region": "Utah",
            "slug": "us_ut_murray",
            "shipping_phone_number": "(801) 876-4117",
            "stripe_location": "tml_EZJF9wduBrhWas"
        },
        {
            "channel": "retail",
            "country": "US",
            "directory_image_url": "",
            "display_city": "Santa Clara",
            "display_location": "Santa Clara",
            "display_name": "Valley Fair ",
            "display_postal_code": "95050",
            "display_state": "CA",
            "display_street_address_1": "2855 Stevens Creek Boulevard",
            "display_street_address_2": " Suite 1715",
            "email": "santaclara@onepeloton.com ",
            "google_maps_url": "https://www.google.com/maps/place/Peloton/@37.3253062,-121.9456084,15z/data=!4m2!3m1!1s0x0:0x619cb90ad49d0adb?sa=X&ved=2ahUKEwjVlbLQ8Y70AhXCQvEDHVPiBAcQ_BJ6BAhKEAU",
            "hero_image_url": "",
            "hours": {
                "mon": "10:00 AM - 9:00 PM",
                "tue": "10:00 AM - 9:00 PM",
                "wed": "10:00 AM - 9:00 PM",
                "thu": "10:00 AM - 9:00 PM",
                "fri": "10:00 AM - 9:00 PM",
                "sat": "10:00 AM - 9:00 PM",
                "sun": "11:00 AM - 8:00 PM"
            },
            "hours_of_operation": [
                "Mon - Sat: 10:00 a.m. - 9:00 p.m",
                " Sun: 11:00 a.m. - 8:00 p.m."
            ],
            "id": "6790a13d691744ca9505d319ce7ad5cd",
            "is_coming_soon": false,
            "is_microstore": false,
            "is_visible": true,
            "is_third_party": false,
            "is_booking_available": true,
            "image_urls": [],
            "latitude": 37.325566,
            "longitude": -121.947189,
            "meta_description": "",
            "meta_title": "",
            "name": "Peloton Santa Clara",
            "phone_ext": "",
            "region": "California",
            "slug": "us_ca_santaclara",
            "shipping_phone_number": "(408) 805-3166 ",
            "stripe_location": "tml_EZCi9wiJFZ6thX"
        },
        {
            "channel": "retail",
            "country": "US",
            "directory_image_url": "https://dmb3ount55sfc.cloudfront.net/retail-images/newportbeach/newportbeach-directory-1.jpg",
            "display_city": "Newport Beach",
            "display_location": "Newport Beach",
            "display_name": "Fashion Island",
            "display_postal_code": "92660",
            "display_state": "CA",
            "display_street_address_1": "401 Newport Center Dr",
            "display_street_address_2": "",
            "email": "newportbeach@onepeloton.com",
            "google_maps_url": "https://www.google.com/maps/place/Peloton/@33.6150912,-117.8780675,17z/data=!3m1!4b1!4m5!3m4!1s0x80dce087baaaaf0b:0x2ba585c8700c3d45!8m2!3d33.6150912!4d-117.8758788",
            "hero_image_url": "https://s3.amazonaws.com/peloton-ride-images/ce16530070c764f956bcb140b91fa33be200ff35/img_1486152906305.jpg",
            "hours": {
                "mon": "10:00 AM - 8:00 PM",
                "tue": "10:00 AM - 8:00 PM",
                "wed": "10:00 AM - 8:00 PM",
                "thu": "10:00 AM - 8:00 PM",
                "fri": "10:00 AM - 8:00 PM",
                "sat": "10:00 AM - 8:00 PM",
                "sun": "11:00 AM - 6:00 PM"
            },
            "hours_of_operation": [
                "Mon - Sat: 10:00 a.m. \u2013 8:00 p.m",
                " Sun: 11:00 a.m. \u2013 6:00 p.m"
            ],
            "id": "09cb11228abd46009ea906d33f5020bd",
            "is_coming_soon": false,
            "is_microstore": false,
            "is_visible": true,
            "is_third_party": false,
            "is_booking_available": true,
            "image_urls": [
                "https://dmb3ount55sfc.cloudfront.net/retail-images/newportbeach/newportbeach-storefront.jpg",
                "https://dmb3ount55sfc.cloudfront.net/retail-images/newportbeach/newportbeach-interior-2.jpg",
                "https://dmb3ount55sfc.cloudfront.net/retail-images/newportbeach/newportbeach-interior-1.jpg"
            ],
            "latitude": 33.615841,
            "longitude": -117.876727,
            "meta_description": "Newport Beach (Fashion Island) - 401 Newport Center Dr.Newport Beach, CA 92660, 866-679-9129 x 607. Hours and contact information for our Newport Beach, CA retail location.",
            "meta_title": "Newport Beach (Fashion Island) Store",
            "name": "Peloton Newport Beach",
            "phone_ext": "",
            "region": "California",
            "slug": "us_ca_newportbeach",
            "shipping_phone_number": "(949) 379-1588",
            "stripe_location": "tml_EZJF4gKcqzVtmX"
        },{
            "channel": "retail",
            "country": "US",
            "directory_image_url": "",
            "display_city": "San Diego",
            "display_location": "San Diego ",
            "display_name": "Westfield UTC ",
            "display_postal_code": "92122",
            "display_state": "CA",
            "display_street_address_1": "4545 La Jolla Village Drive ",
            "display_street_address_2": "",
            "email": "sandiego@onepeloton.com ",
            "google_maps_url": "https://www.google.com/maps/place/Peloton/@32.8710475,-117.2134107,15z/data=!4m2!3m1!1s0x0:0xe5cabe0bc231cd09?sa=X&ved=2ahUKEwjt1r2i8Y70AhXpSPEDHbY9AgcQ_BJ6BAhkEAU",
            "hero_image_url": "",
            "hours": {
                "mon": "10:00 AM \u2013 8:00 PM",
                "tue": "10:00 AM \u2013 8:00 PM",
                "wed": "10:00 AM \u2013 8:00 PM",
                "thu": "10:00 AM \u2013 8:00 PM",
                "fri": "10:00 AM \u2013 8:00 PM",
                "sat": "10:00 AM \u2013 8:00 PM",
                "sun": "11:00 AM \u2013 7:00 PM"
            },
            "hours_of_operation": [
                "Mon - Thurs: 11:00 a.m. - 8:00 p.m.",
                " Fri- Sat: 10:00 a.m.- 8:00 p.m.",
                " Sun: 10:00 a.m. - 6:00 p.m."
            ],
            "id": "2ce6a4e5884c4350b1a4f3e65d8fe49f",
            "is_coming_soon": false,
            "is_microstore": false,
            "is_visible": true,
            "is_third_party": false,
            "is_booking_available": true,
            "image_urls": [],
            "latitude": 32.87093,
            "longitude": -117.212992,
            "meta_description": "",
            "meta_title": "",
            "name": "Peloton San Diego",
            "phone_ext": "",
            "region": "California",
            "slug": "us_ca_sandiego",
            "shipping_phone_number": "(619) 727-6960 ",
            "stripe_location": "tml_EZJF6QlbEdtEdz"
        },{
            "channel": "retail",
            "country": "US",
            "directory_image_url": "",
            "display_city": "Lone Tree",
            "display_location": "Lone Tree",
            "display_name": "Park Meadows",
            "display_postal_code": "80124",
            "display_state": "CO",
            "display_street_address_1": "8505  Park Meadows Center Dr",
            "display_street_address_2": "",
            "email": "lonetree@onepeloton.com",
            "google_maps_url": "https://www.google.com/maps/place/Peloton/@39.561773,-104.8770737,17z/data=!3m1!4b1!4m5!3m4!1s0x876c85f3a6ce631f:0x8b50a3c0f6172d5b!8m2!3d39.561773!4d-104.874885",
            "hero_image_url": "https://s3.amazonaws.com/peloton-ride-images/a2869e63fd2be4877a0ffcae4580b7cc2e8b8890/img_1526999796308.jpg",
            "hours": {
                "mon": "10:00 AM - 8:00 PM",
                "tue": "10:00 AM - 8:00 PM",
                "wed": "10:00 AM - 8:00 PM",
                "thu": "10:00 AM - 8:00 PM",
                "fri": "10:00 AM - 8:00 PM",
                "sat": " 10:00 AM - 8:00 PM",
                "sun": "11:00 AM - 6:00 PM"
            },
            "hours_of_operation": [
                "Mon - Sat: 10:00 a.m. - 8:00 p.m.",
                " Sun: 11:00 a.m. - 6:00 p.m."
            ],
            "id": "eca5bb5146c24e18b4b66e321f37bf0e",
            "is_coming_soon": false,
            "is_microstore": false,
            "is_visible": true,
            "is_third_party": false,
            "is_booking_available": true,
            "image_urls": [
                "https://s3.amazonaws.com/peloton-ride-images/a2869e63fd2be4877a0ffcae4580b7cc2e8b8890/img_1526999796308.jpg"
            ],
            "latitude": 39.560309,
            "longitude": -104.88049,
            "meta_description": "",
            "meta_title": "",
            "name": "Peloton Lone Tree",
            "phone_ext": "",
            "region": "Colorado",
            "slug": "us_co_lonetree_2",
            "shipping_phone_number": "(720) 513-7366",
            "stripe_location": "tml_EZJGCQXZAl2t94"
        },
        {
            "channel": "retail",
            "country": "US",
            "directory_image_url": "https://s3.amazonaws.com/peloton-ride-images/406e2f2133ff05accd9eead99a53306606a76d8b/img_1465674885823.jpg",
            "display_city": "Houston",
            "display_location": "Houston",
            "display_name": "The Galleria",
            "display_postal_code": "77056",
            "display_state": "TX",
            "display_street_address_1": "5135 W Alabama St",
            "display_street_address_2": "space 5340",
            "email": "houston@onepeloton.com",
            "google_maps_url": "https://www.google.com/maps/place/Peloton/@29.7363092,-95.4657334,17z/data=!3m1!4b1!4m5!3m4!1s0x8640c16eb431bffb:0x7b2ff15d0e1d7113!8m2!3d29.7363092!4d-95.4635447",
            "hero_image_url": "",
            "hours": {
                "mon": "11:00 AM - 8:00 PM",
                "tue": "11:00 AM - 8:00 PM",
                "wed": "11:00 AM - 8:00 PM",
                "thu": "11:00 AM - 8:00 PM",
                "fri": "10:00 AM - 9:00 PM",
                "sat": "10:00 AM - 9:00 PM",
                "sun": "12:00 AM - 7:00 PM"
            },
            "hours_of_operation": [
                "Mon - Thur: 11:00 a.m. - 8:00 p.m.",
                " Fri - Sat: 10:00 a.m. - 9:00 p.m., Sun: 12:00 p.m. - 7:00 p.m."
            ],
            "id": "beb2a12b43374eb5b3b23bab0dc8bbb1",
            "is_coming_soon": false,
            "is_microstore": false,
            "is_visible": false,
            "is_third_party": false,
            "is_booking_available": true,
            "image_urls": [
                "https://s3.amazonaws.com/peloton-ride-images/406e2f2133ff05accd9eead99a53306606a76d8b/img_1465659553476.jpg"
            ],
            "latitude": 29.737432,
            "longitude": -95.465636,
            "meta_description": "The Galleria - 5135 West Alabama Street space 5340 Houston, TX 77056, 866-679-9129 x 637. Hours and contact information for our Houston, TX retail location.",
            "meta_title": "Houston, TX Store",
            "name": "Peloton Houston",
            "phone_ext": "(281) 688-6491",
            "region": "Texas",
            "slug": "us_tx_houston",
            "shipping_phone_number": "(281) 688-6499",
            "stripe_location": "tml_EZCjBwsblCW88n"
        },
        {
            "channel": "retail",
            "country": "US",
            "directory_image_url": "https://dmb3ount55sfc.cloudfront.net/retail-images/chicago/chicago-directory.jpg",
            "display_city": "Oak Brook",
            "display_location": "Oak Brook",
            "display_name": "Oakbrook Center",
            "display_postal_code": "60523",
            "display_state": "IL",
            "display_street_address_1": "69 Oakbrook Center",
            "display_street_address_2": "",
            "email": "oakbrook@onepeloton.com",
            "google_maps_url": "https://www.google.com/maps/place/Peloton/@41.8498021,-87.9559678,17z/data=!3m2!4b1!5s0x880e4c429c54bd37:0x7edf0a3a46edbf3c!4m5!3m4!1s0x880e4c68227375cf:0x2ba14d872fa4a4a9!8m2!3d41.8498021!4d-87.9537791",
            "hero_image_url": "",
            "hours": {
                "mon": "10:00 AM \u2013 8:00 PM",
                "tue": "10:00 AM \u2013 8:00 PM",
                "wed": "10:00 AM \u2013 8:00 PM",
                "thu": "10:00 AM \u2013 8:00 PM",
                "fri": "10:00 AM \u2013 9:00 PM",
                "sat": "10:00 AM \u2013 9:00 PM",
                "sun": "11:00 AM \u2013 6:00 PM"
            },
            "hours_of_operation": [
                "Mon - Thurs: 10:00 a.m. - 8:00 p.m.",
                "Fri - Sat: 10:00 a.m. - 9:00 p.m.",
                " Sun: 11:00 a.m. - 6:00 p.m."
            ],
            "id": "fb657f8431104463ac3259e6d70bc6a2",
            "is_coming_soon": false,
            "is_microstore": false,
            "is_visible": true,
            "is_third_party": false,
            "is_booking_available": true,
            "image_urls": [
                "https://dmb3ount55sfc.cloudfront.net/retail-images/chicago/chicago-storefront-1.jpg",
                "https://dmb3ount55sfc.cloudfront.net/retail-images/chicago/chicago-storefront-2.jpg",
                "https://dmb3ount55sfc.cloudfront.net/retail-images/chicago/chicago-storefront-3.jpg"
            ],
            "latitude": 41.849811,
            "longitude": -87.956011,
            "meta_description": "",
            "meta_title": "Chicago, Oak Brook, IL Store",
            "name": "Peloton Oak Brook",
            "phone_ext": "",
            "region": "Illinois",
            "slug": "us_il_oakbrook",
            "shipping_phone_number": "(331) 244-7766",
            "stripe_location": "tml_EZJGCwj5s859Iv"
        },
        {
            "channel": "retail",
            "country": "US",
            "directory_image_url": "https://dmb3ount55sfc.cloudfront.net/retail-images/dallas/jan2016/dallas-directory.jpg",
            "display_city": "Dallas",
            "display_location": "Dallas",
            "display_name": "NorthPark Center",
            "display_postal_code": "75225",
            "display_state": "TX",
            "display_street_address_1": "8687 North Central Expressway",
            "display_street_address_2": "Space #762",
            "email": "dallas@onepeloton.com",
            "google_maps_url": "https://www.google.com/maps/place/Peloton/@32.8685017,-96.7757012,17z/data=!3m1!4b1!4m5!3m4!1s0x864e9fbe89dbd5db:0xc346d54c9c8da4f3!8m2!3d32.8685017!4d-96.7735125",
            "hero_image_url": "https://s3.amazonaws.com/peloton-ride-images/8014457d2b8b65c6626632da23f2e161f0d5e5c2/img_1486155355977.jpg",
            "hours": {
                "mon": "10:00 AM \u2013 8:00 PM",
                "tue": "10:00 AM \u2013 8:00 PM",
                "wed": "10:00 AM \u2013 8:00 PM",
                "thu": "10:00 AM \u2013 8:00 PM",
                "fri": "10:00 AM \u2013 8:00 PM",
                "sat": "10:00 AM \u2013 8:00 PM",
                "sun": "12:00 PM \u2013 6:00 PM"
            },
            "hours_of_operation": [
                "Mon - Sat: 11:00 a.m. - 7:00 p.m.",
                "Sun: 12:00 p.m. - 6:00 p.m."
            ],
            "id": "8a442becc94c4ad9b1683d5f78ad5ae5",
            "is_coming_soon": false,
            "is_microstore": false,
            "is_visible": true,
            "is_third_party": false,
            "is_booking_available": true,
            "image_urls": [
                "https://dmb3ount55sfc.cloudfront.net/retail-images/dallas/jan2016/dallas-storefront-1.jpg",
                "https://dmb3ount55sfc.cloudfront.net/retail-images/dallas/jan2016/dallas-interior-5.jpg",
                "https://dmb3ount55sfc.cloudfront.net/retail-images/dallas/jan2016/dallas-interior-2.jpg",
                "https://dmb3ount55sfc.cloudfront.net/retail-images/dallas/jan2016/dallas-interior-6.jpg",
                "https://dmb3ount55sfc.cloudfront.net/retail-images/dallas/jan2016/dallas-interior-1.jpg",
                "https://dmb3ount55sfc.cloudfront.net/retail-images/dallas/jan2016/dallas-interior-3.jpg"
            ],
            "latitude": 32.86874,
            "longitude": -96.774047,
            "meta_description": "NorthPark Center - 8687 N Central Expressway Suite 1428 Dallas 75225, 866-679-9129 x 551. Hours and contact information for our Dallas, TX retail location.",
            "meta_title": "Dallas, TX Store",
            "name": "Peloton Dallas",
            "phone_ext": "",
            "region": "Texas",
            "slug": "us_tx_dallas",
            "shipping_phone_number": "(214) 504-2951",
            "stripe_location": "tml_EZCiAtGIZ2WUMp"
        }, {
            "channel": "retail",
            "country": "US",
            "directory_image_url": "",
            "display_city": "Alpharetta",
            "display_location": "Alpharetta",
            "display_name": "Avalon",
            "display_postal_code": "30009",
            "display_state": "GA",
            "display_street_address_1": "8140 Avalon Boulevard",
            "display_street_address_2": "Suite 8140",
            "email": "Alpharetta@onepeloton.com ",
            "google_maps_url": "https://www.google.com/maps/place/Peloton/@34.0705148,-84.2744188,15z/data=!4m5!3m4!1s0x0:0x301f1b5e8ec80e9e!8m2!3d34.0705991!4d-84.2744199",
            "hero_image_url": "",
            "hours": {
                "mon": "10:00 AM \u2013 8:00 PM",
                "tue": "10:00 AM \u2013 8:00 PM",
                "wed": "10:00 AM \u2013 8:00 PM",
                "thu": "10:00 AM \u2013 8:00 PM",
                "fri": "10:00 AM \u2013 9:00 PM",
                "sat": "10:00 AM \u2013 9:00 PM",
                "sun": "12:00 PM - 6:00 PM"
            },
            "hours_of_operation": [
                "Mon - Sat: 10:00 a.m. - 8:00 p.m.",
                "Sun: 11:00 p.m. - 6:00 p.m."
            ],
            "id": "8154fafae0604e649cf67f5e3becfe02",
            "is_coming_soon": false,
            "is_microstore": false,
            "is_visible": true,
            "is_third_party": false,
            "is_booking_available": true,
            "image_urls": [],
            "latitude": 34.070559,
            "longitude": -84.27664,
            "meta_description": "",
            "meta_title": "",
            "name": "Peloton Alpharetta",
            "phone_ext": "(678) 578.6279",
            "region": "Georgia",
            "slug": "us_ga_alpharetta",
            "shipping_phone_number": "(678) 578-6279",
            "stripe_location": "tml_EZCiwObhwLrDkQ"
        },{
            "channel": "retail",
            "country": "US",
            "directory_image_url": "",
            "display_city": "Raleigh ",
            "display_location": "Raleigh ",
            "display_name": "Raleigh ",
            "display_postal_code": "27609",
            "display_state": "NC",
            "display_street_address_1": "4120 Main at North Hills Street",
            "display_street_address_2": "Space #K115/K120",
            "email": "raleigh@onepeloton.com ",
            "google_maps_url": "https://www.google.com/maps/place/4120+Main+at+North+Hills+St+Space+%23K115%2FK120,+Raleigh,+NC+27609/@35.8363717,-78.6452753,17z/data=!4m13!1m7!3m6!1s0x89ac5897231a8847:0x369be39fd4203fc9!2s4120+Main+at+North+Hills+St+Space+%23K115%2FK120,+Raleigh,+NC+27609!3b1!8m2!3d35.8363674!4d-78.6430866!3m4!1s0x89ac5897231a8847:0x369be39fd4203fc9!8m2!3d35.8363674!4d-78.6430866",
            "hero_image_url": "",
            "hours": {
                "mon": "10:00 AM - 7:00 PM",
                "tue": "10:00 AM - 7:00 PM",
                "wed": "10:00 AM - 7:00 PM",
                "thu": "10:00 AM - 7:00 PM",
                "fri": "10:00 AM - 7:00 PM",
                "sat": "10:00 AM - 7:00 PM",
                "sun": "12:00 PM - 6:00 PM"
            },
            "hours_of_operation": [
                "Mon-Sun: 9am-9pm "
            ],
            "id": "32499094deb34c69ab103f83a0fd8878",
            "is_coming_soon": false,
            "is_microstore": true,
            "is_visible": true,
            "is_third_party": false,
            "is_booking_available": true,
            "image_urls": [],
            "latitude": 35.836372,
            "longitude": -78.645275,
            "meta_description": "",
            "meta_title": "",
            "name": "Peloton Raleigh",
            "phone_ext": "",
            "region": "North Carolina ",
            "slug": "us_nc_raleigh",
            "shipping_phone_number": "(919) 355-0101",
            "stripe_location": "tml_EZCi6wB213mCEh"
        },{
            "channel": "retail",
            "country": "US",
            "directory_image_url": "",
            "display_city": "Cherry Hill",
            "display_location": "Cherry Hill",
            "display_name": "Cherry Hill Mall",
            "display_postal_code": "08002",
            "display_state": "NJ",
            "display_street_address_1": "2000 NJ-38",
            "display_street_address_2": "Ste 1720 ",
            "email": "cherryhill@onepeloton.com",
            "google_maps_url": "https://www.google.com/maps/place/Peloton/@39.9413237,-75.028149,17z/data=!4m8!1m2!2m1!1sPeloton+at+Cherry+Hill+Mall+2000+NJ-38+Cherry+Hill,+NJ+08002!3m4!1s0x89c6cbaaa1476e93:0xf718f548f0de7f5d!8m2!3d39.94086!4d-75.0257016",
            "hero_image_url": "",
            "hours": {
                "mon": "11:00 AM - 8:00 PM",
                "tue": "11:00 AM - 8:00 PM",
                "wed": "11:00 AM - 8:00 PM",
                "thu": "11:00 AM - 8:00 PM",
                "fri": "10:00 AM - 9:00 PM",
                "sat": "10:00 AM - 9:00 PM",
                "sun": "11:00 AM - 6:00 PM"
            },
            "hours_of_operation": [
                "Mon -Thurs: 11:00 a.m. - 7:00 p.m",
                " Fri-Sat: 11:00 a.m. - 6:00p.m",
                " Sun: 11:00 a.m. - 6:00 p.m."
            ],
            "id": "288a4ad8625e4094ba4f5083e2e37c14",
            "is_coming_soon": false,
            "is_microstore": false,
            "is_visible": true,
            "is_third_party": false,
            "is_booking_available": true,
            "image_urls": [],
            "latitude": 39.940632,
            "longitude": -75.028689,
            "meta_description": "",
            "meta_title": "",
            "name": "Peloton Cherry Hill",
            "phone_ext": "",
            "region": "New Jersey",
            "slug": "us_nj_cherryhill_2",
            "shipping_phone_number": "(856) 263-2463",
            "stripe_location": "tml_EZJF6AAHWKqDm8"
        },{
            "channel": "retail",
            "country": "US",
            "directory_image_url": "https://dmb3ount55sfc.cloudfront.net/retail-images/washingtondc/washingtondc-directory.jpg",
            "display_city": "Tysons Corner",
            "display_location": "Tysons Corner",
            "display_name": "Tysons Corner Center",
            "display_postal_code": "22102",
            "display_state": "VA",
            "display_street_address_1": "1961 Chain Bridge Rd",
            "display_street_address_2": "",
            "email": "tysonscorner@onepeloton.com",
            "google_maps_url": "https://www.google.com/maps/place/Peloton/@38.9181494,-77.2234345,17z/data=!3m2!4b1!5s0x89b64ae8843410c5:0xf16df7f7e05fef1b!4m5!3m4!1s0x89b64ae8edb958fd:0xa836eff8c9b719bd!8m2!3d38.9181494!4d-77.2212458",
            "hero_image_url": "https://s3.amazonaws.com/peloton-ride-images/5cdc3741e4330806e4382b80daa6246e4efd3ba5/img_1486150636232.jpg",
            "hours": {
                "mon": "10:00 AM - 9:00 PM ",
                "tue": "10:00 AM - 9:00 PM ",
                "wed": "10:00 AM - 9:00 PM ",
                "thu": "10:00 AM - 9:00 PM ",
                "fri": "10:00 AM - 9:00 PM ",
                "sat": "10:00 AM - 9:00 PM ",
                "sun": "11:00 AM - 7:00 PM "
            },
            "hours_of_operation": [
                "Mon-Thurs:11:00 a.m. - 7:00 p.m.",
                " Fri-Sat: 10:00 a.m - 8:00 p.m.",
                "  Sun: 11:00 p.m. - 7:00 p.m."
            ],
            "id": "c2fe7bffba3a479f874bc12107348bfc",
            "is_coming_soon": false,
            "is_microstore": false,
            "is_visible": true,
            "is_third_party": false,
            "is_booking_available": true,
            "image_urls": [
                "https://dmb3ount55sfc.cloudfront.net/retail-images/washingtondc/washingtondc-storefront-3.jpg"
            ],
            "latitude": 38.917623,
            "longitude": -77.224426,
            "meta_description": "Tysons Corner Center - 961 Chain Bridge Rd, McLean, VA 22102, 866-679-9129 x 513. Hours and contact information for our Washington, D.C. retail location.",
            "meta_title": "Washington D.C. Store",
            "name": "Peloton Tysons Corner",
            "phone_ext": "",
            "region": "Virginia",
            "slug": "us_va_tysonscorner_2",
            "shipping_phone_number": "(703) 872-7288",
            "stripe_location": "tml_EZJGBQPHrt4zuD"
        },{
            "channel": "retail",
            "country": "US",
            "directory_image_url": "https://s3.amazonaws.com/peloton-ride-images/4868e9fc13faec9f341c80023bfa42de6bc39b32/img_1464702056993.jpg",
            "display_city": "East Hampton",
            "display_location": "East Hampton",
            "display_name": "East Hampton",
            "display_postal_code": "11937",
            "display_state": "NY",
            "display_street_address_1": "75 Main St",
            "display_street_address_2": "",
            "email": "easthampton@onepeloton.com",
            "google_maps_url": "https://goo.gl/maps/b42aeVwbjLK2",
            "hero_image_url": "",
            "hours": {
                "wed": "CLOSED",
                "sun": "CLOSED",
                "fri": "CLOSED",
                "tue": "CLOSED",
                "mon": "CLOSED",
                "thu": "CLOSED",
                "sat": "CLOSED"
            },
            "hours_of_operation": [
                "Sun - Sat: 10:00 a.m. - 6:00 p.m"
            ],
            "id": "b1687e7bc42f41c7933be3f3f706c065",
            "is_coming_soon": false,
            "is_microstore": false,
            "is_visible": false,
            "is_third_party": false,
            "is_booking_available": true,
            "image_urls": [
                "https://s3.amazonaws.com/peloton-ride-images/4868e9fc13faec9f341c80023bfa42de6bc39b32/img_1464702737328.jpg"
            ],
            "latitude": 40.962462,
            "longitude": -72.189035,
            "meta_description": "",
            "meta_title": "",
            "name": "Peloton East Hampton",
            "phone_ext": "",
            "region": "New York",
            "slug": "east-hampton",
            "shipping_phone_number": "(646) 290-6334",
            "stripe_location": "tml_EZJGAQ51El3ia2"
        },
        {
            "channel": "retail",
            "country": "US",
            "directory_image_url": "https://dmb3ount55sfc.cloudfront.net/retail-images/chicago/chicago-directory.jpg",
            "display_city": "Oak Brook",
            "display_location": "Oak Brook",
            "display_name": "Oakbrook Center",
            "display_postal_code": "60523",
            "display_state": "IL",
            "display_street_address_1": "69 Oakbrook Center",
            "display_street_address_2": "",
            "email": "oakbrook@onepeloton.com",
            "google_maps_url": "https://www.google.com/maps/place/Peloton/@41.8498021,-87.9559678,17z/data=!3m2!4b1!5s0x880e4c429c54bd37:0x7edf0a3a46edbf3c!4m5!3m4!1s0x880e4c68227375cf:0x2ba14d872fa4a4a9!8m2!3d41.8498021!4d-87.9537791",
            "hero_image_url": "",
            "hours": {
                "mon": "10:00 AM \u2013 8:00 PM",
                "tue": "10:00 AM \u2013 8:00 PM",
                "wed": "10:00 AM \u2013 8:00 PM",
                "thu": "10:00 AM \u2013 8:00 PM",
                "fri": "10:00 AM \u2013 9:00 PM",
                "sat": "10:00 AM \u2013 9:00 PM",
                "sun": "11:00 AM \u2013 6:00 PM"
            },
            "hours_of_operation": [
                "Mon - Thurs: 10:00 a.m. - 8:00 p.m.",
                "Fri - Sat: 10:00 a.m. - 9:00 p.m.",
                " Sun: 11:00 a.m. - 6:00 p.m."
            ],
            "id": "fb657f8431104463ac3259e6d70bc6a2",
            "is_coming_soon": false,
            "is_microstore": false,
            "is_visible": true,
            "is_third_party": false,
            "is_booking_available": true,
            "image_urls": [
                "https://dmb3ount55sfc.cloudfront.net/retail-images/chicago/chicago-storefront-1.jpg",
                "https://dmb3ount55sfc.cloudfront.net/retail-images/chicago/chicago-storefront-2.jpg",
                "https://dmb3ount55sfc.cloudfront.net/retail-images/chicago/chicago-storefront-3.jpg"
            ],
            "latitude": 41.849811,
            "longitude": -87.956011,
            "meta_description": "",
            "meta_title": "Chicago, Oak Brook, IL Store",
            "name": "Peloton Oak Brook",
            "phone_ext": "",
            "region": "Illinois",
            "slug": "us_il_oakbrook",
            "shipping_phone_number": "(331) 244-7766",
            "stripe_location": "tml_EZJGCwj5s859Iv"
        },{
            "channel": "retail",
            "country": "US",
            "directory_image_url": "https://s3.amazonaws.com/peloton-ride-images/c141aa1e0d0db3a1a40dda4ab43f02f48759d10d/img_1472825567945.jpg",
            "display_city": "Troy",
            "display_location": "Troy",
            "display_name": "Somerset Collection",
            "display_postal_code": "48084",
            "display_state": "MI",
            "display_street_address_1": "2800 W Big Beaver Rd",
            "display_street_address_2": "",
            "email": "troy@onepeloton.com",
            "google_maps_url": "https://www.google.com/maps/place/Peloton/@42.5630759,-83.184354,15z/data=!4m2!3m1!1s0x0:0x4283daf01b76771?sa=X&ved=2ahUKEwiBh-vu6470AhW8VTABHZW-CEgQ_BJ6BAhhEAU",
            "hero_image_url": "",
            "hours": {
                "mon": "10:00 AM - 8:00 PM",
                "tue": "10:00 AM - 8:00 PM",
                "wed": "10:00 AM - 8:00 PM",
                "thu": "10:00 AM - 8:00 PM",
                "fri": "10:00 AM - 8:00 PM",
                "sat": "10:00 AM - 8:00 PM",
                "sun": "12:00 PM \u2013 6:00 PM"
            },
            "hours_of_operation": [
                "Mon - Sat: 10:00 a.m. - 7:00 p.m.",
                "Sun: 11:00 a.m. - 7:00 p.m."
            ],
            "id": "30cc1e7549a54363bcea7e4759280212",
            "is_coming_soon": false,
            "is_microstore": false,
            "is_visible": true,
            "is_third_party": false,
            "is_booking_available": true,
            "image_urls": [
                "https://s3.amazonaws.com/peloton-ride-images/19c3f2f5f55f7e773b6b47953605c9be319aed45/img_1474116500937.jpg"
            ],
            "latitude": 42.563076,
            "longitude": -83.186537,
            "meta_description": "",
            "meta_title": "",
            "name": "Peloton Troy",
            "phone_ext": "",
            "region": "Michigan",
            "slug": "detroit",
            "shipping_phone_number": "(248) 215-0094",
            "stripe_location": "tml_EZJF6Qm0a3KAHw"
        },
        {
            "channel": "retail",
            "country": "CA",
            "directory_image_url": "",
            "display_city": "Etobicoke",
            "display_location": "Etobicoke",
            "display_name": "Sherway Gardens",
            "display_postal_code": "M9C 1B8 ",
            "display_state": "Ontario",
            "display_street_address_1": "25 The West Mall",
            "display_street_address_2": "",
            "email": "etobicoke@onepeloton.ca",
            "google_maps_url": "https://www.google.com/maps/place/Peloton/@43.6117865,-79.5571401,15z/data=!4m5!3m4!1s0x0:0xdd37e933d3d34d5f!8m2!3d43.6117865!4d-79.5571401",
            "hero_image_url": "",
            "hours": {
                "mon": "10:00 AM - 9:00 PM",
                "tue": "10:00 AM - 9:00 PM",
                "wed": "10:00 AM - 9:00 PM",
                "thu": "10:00 AM - 9:00 PM",
                "fri": "10:00 AM - 9:00 PM",
                "sat": "10:00 AM - 9:00 PM",
                "sun": "10:00 AM - 6:00 PM"
            },
            "hours_of_operation": [
                "Mon - Sat 11:00 a.m. - 7:00 p.m.",
                " Sun: 11:00 a.m. - 6:00 p.m."
            ],
            "id": "4e9aae667cb94aceaa893e535013d2c2",
            "is_coming_soon": false,
            "is_microstore": false,
            "is_visible": true,
            "is_third_party": false,
            "is_booking_available": true,
            "image_urls": [],
            "latitude": 43.6119,
            "longitude": -79.557105,
            "meta_description": "",
            "meta_title": "",
            "name": "CA Etobicoke",
            "phone_ext": "",
            "region": "Ontario",
            "slug": "ca_on_etobicoke_2",
            "shipping_phone_number": "(647) 932-5580 ",
            "stripe_location": "tml_EZJF8A8VLckfEr"
        }
    ]

}